MANIFEST.in
README.rst
setup.py
chr.egg-info/PKG-INFO
chr.egg-info/SOURCES.txt
chr.egg-info/dependency_links.txt
chr.egg-info/entry_points.txt
chr.egg-info/not-zip-safe
chr.egg-info/requires.txt
chr.egg-info/top_level.txt
chru/__init__.py
chru/chra.py
chru/version.py
chru/api/__init__.py
chru/api/manager.py
chru/api/web/__init__.py
chru/api/web/v1.py
chru/utility/__init__.py
chru/utility/base62.py
chru/utility/funcs.py
chru/utility/struct.py
chru/web/__init__.py
chru/web/routes.py
chru/web/settings.py
chru/web/slug.py
chru/web/static/960.css
chru/web/static/flashes.js
chru/web/static/index.js
chru/web/static/main.css
chru/web/static/jqplot/jqplot.barRenderer.min.js
chru/web/static/jqplot/jqplot.categoryAxisRenderer.min.js
chru/web/static/jqplot/jqplot.cursor.min.js
chru/web/static/jqplot/jqplot.highlighter.min.js
chru/web/static/jqplot/jqplot.pieRenderer.min.js
chru/web/static/jqplot/jqplot.pointLabels.min.js
chru/web/static/jqplot/jquery.jqplot.min.css
chru/web/static/jqplot/jquery.jqplot.min.js
chru/web/templates/index.html
chru/web/templates/layout.html
chru/web/templates/stats.html