Metadata-Version: 1.1
Name: chr
Version: 2.1.0
Summary: Python based URL shortening service
Home-page: https://github.com/plausibility/chr
Author: plausibility
Author-email: chris@gibsonsec.org
License: MIT
Keywords: url short shortener slug
Platform: UNKNOWN
Classifier: Development Status :: 4 - Beta
Classifier: Intended Audience :: System Administrators
Classifier: License :: OSI Approved :: MIT License
Classifier: Operating System :: POSIX :: Linux
Classifier: Programming Language :: Python :: 2
